MANIFEST.in
README
setup.py
django_photo_albums.egg-info/PKG-INFO
django_photo_albums.egg-info/SOURCES.txt
django_photo_albums.egg-info/dependency_links.txt
django_photo_albums.egg-info/requires.txt
django_photo_albums.egg-info/top_level.txt
photo_albums/__init__.py
photo_albums/forms.py
photo_albums/models.py
photo_albums/test_utils.py
photo_albums/urls.py
photo_albums/views.py
photo_albums/lib/__init__.py
photo_albums/lib/zipfile.py
photo_albums/locale/en/LC_MESSAGES/django.mo
photo_albums/locale/en/LC_MESSAGES/django.po
photo_albums/locale/ru/LC_MESSAGES/django.mo
photo_albums/locale/ru/LC_MESSAGES/django.po