Metadata-Version: 1.1
Name: django-photo-albums
Version: 0.20.2
Summary: Pluggable Django image gallery app.
Home-page: http://bitbucket.org/kmike/django-photo-albums/
Author: Mikhail Korobov
Author-email: kmike84@gmail.com
License: MIT license
Platform: UNKNOWN
Classifier: Development Status :: 3 - Alpha
Classifier: Environment :: Web Environment
Classifier: Framework :: Django
Classifier: Intended Audience :: Developers
Classifier: License :: OSI Approved :: MIT License
Classifier: Programming Language :: Python
Classifier: Topic :: Software Development :: Libraries :: Python Modules
Requires: django (>=1.1)
